chrome_delete.py
delete_chrome_history_py-0.1.8.dist-info/DESCRIPTION.rst
delete_chrome_history_py-0.1.8.dist-info/METADATA
delete_chrome_history_py-0.1.8.dist-info/RECORD
delete_chrome_history_py-0.1.8.dist-info/WHEEL
delete_chrome_history_py-0.1.8.dist-info/metadata.json
delete_chrome_history_py-0.1.8.dist-info/top_level.txt
